collective.dms.mailcontent-1.16.0-py3.11-nspkg.pth
collective/dms/mailcontent/__init__.py
collective/dms/mailcontent/behaviors.py
collective/dms/mailcontent/behaviors.zcml
collective/dms/mailcontent/configure.zcml
collective/dms/mailcontent/dmsincomingmail_icon.png
collective/dms/mailcontent/dmsmail.py
collective/dms/mailcontent/dmsoutgoingmail_icon.png
collective/dms/mailcontent/indexers.py
collective/dms/mailcontent/permissions.zcml
collective/dms/mailcontent/setuphandlers.py
collective/dms/mailcontent/testing.py
collective/dms/mailcontent/testing.zcml
collective/dms/mailcontent/vocabularies.py
collective/dms/mailcontent/browser/__init__.py
collective/dms/mailcontent/browser/configure.zcml
collective/dms/mailcontent/browser/reply_form.py
collective/dms/mailcontent/browser/settings.py
collective/dms/mailcontent/browser/utils.py
collective/dms/mailcontent/browser/views.py
collective/dms/mailcontent/locales/collective.dms.mailcontent.pot
collective/dms/mailcontent/locales/manual.pot
collective/dms/mailcontent/locales/plone.pot
collective/dms/mailcontent/locales/update.sh
collective/dms/mailcontent/locales/en/LC_MESSAGES/collective.dms.mailcontent.po
collective/dms/mailcontent/locales/en/LC_MESSAGES/plone.po
collective/dms/mailcontent/locales/fr/LC_MESSAGES/collective.dms.mailcontent.po
collective/dms/mailcontent/locales/fr/LC_MESSAGES/plone.po
collective/dms/mailcontent/profiles/default/catalog.xml
collective/dms/mailcontent/profiles/default/collective_dms_mailcontent_marker.txt
collective/dms/mailcontent/profiles/default/controlpanel.xml
collective/dms/mailcontent/profiles/default/import_steps.xml
collective/dms/mailcontent/profiles/default/metadata.xml
collective/dms/mailcontent/profiles/default/registry.xml
collective/dms/mailcontent/profiles/default/rolemap.xml
collective/dms/mailcontent/profiles/default/types.xml
collective/dms/mailcontent/profiles/default/types/dmsincomingmail.xml
collective/dms/mailcontent/profiles/default/types/dmsoutgoingmail.xml
collective.dms.mailcontent-1.16.0.dist-info/METADATA
collective.dms.mailcontent-1.16.0.dist-info/WHEEL
collective.dms.mailcontent-1.16.0.dist-info/entry_points.txt
collective.dms.mailcontent-1.16.0.dist-info/namespace_packages.txt
collective.dms.mailcontent-1.16.0.dist-info/top_level.txt
collective.dms.mailcontent-1.16.0.dist-info/RECORD
