Metadata-Version: 2.1
Name: collective.dms.mailcontent
Version: 1.16.0
Summary: Mail content type for document management system
Home-page: https://github.com/collective/collective.dms.mailcontent
Download-URL: https://pypi.org/project/collective.dms.mailcontent
Author: Ecreall, Entrouvert, IMIO
Author-email: cedricmessiant@ecreall.com
License: gpl
Keywords: document management system dms mail
Classifier: Development Status :: 5 - Production/Stable
Classifier: Environment :: Web Environment
Classifier: Framework :: Plone
Classifier: Framework :: Plone :: 4.2
Classifier: Framework :: Plone :: 4.3
Classifier: License :: OSI Approved :: GNU General Public License v2 (GPLv2)
Classifier: Operating System :: OS Independent
Classifier: Programming Language :: Python
Classifier: Programming Language :: Python :: 2
Classifier: Programming Language :: Python :: 2.7
Classifier: Topic :: Software Development :: Libraries :: Python Modules
Requires-Dist: Products.contentmigration
Requires-Dist: setuptools
Requires-Dist: plone.api
Requires-Dist: plone.app.dexterity
Requires-Dist: plone.directives.form
Requires-Dist: collective.contact.core
Requires-Dist: collective.dexteritytextindexer
Requires-Dist: collective.dms.basecontent
Requires-Dist: imio.helpers >=0.55
Requires-Dist: plone.formwidget.datetime
Requires-Dist: five.grok
Provides-Extra: test
Requires-Dist: plone.app.testing ; extra == 'test'
Requires-Dist: unittest2 ; extra == 'test'
Requires-Dist: ecreall.helpers.testing ; extra == 'test'
